url_is_in/__init__.py
url_is_in/prefix_matcher.py
url_is_in-0.1.0.dist-info/METADATA
url_is_in-0.1.0.dist-info/WHEEL
url_is_in-0.1.0.dist-info/licenses/LICENSE
url_is_in-0.1.0.dist-info/RECORD
