Metadata-Version: 2.4
Name: url-is-in
Version: 0.1.0
Summary: A Python package for efficiently checking if a URL is part of large whitelist or blacklist of URLs and domain names.
Project-URL: Homepage, https://github.com/commoncrawl/url-is-in
Project-URL: Repository, https://github.com/commoncrawl/url-is-in.git
Project-URL: Issues, https://github.com/commoncrawl/url-is-in/issues
Project-URL: Documentation, https://github.com/commoncrawl/url-is-in#readme
Author-email: Malte Ostendorff <malte@commoncrawl.org>
License: Apache-2.0
License-File: LICENSE
Keywords: blacklist,domain,filtering,matching,surt,url,web-crawling,whitelist
Classifier: Development Status :: 4 - Beta
Classifier: Intended Audience :: Developers
Classifier: License :: OSI Approved :: Apache Software License
Classifier: Operating System :: OS Independent
Classifier: Programming Language :: Python :: 3
Classifier: Programming Language :: Python :: 3.8
Classifier: Programming Language :: Python :: 3.9
Classifier: Programming Language :: Python :: 3.10
Classifier: Programming Language :: Python :: 3.11
Classifier: Programming Language :: Python :: 3.12
Classifier: Topic :: Internet :: WWW/HTTP
Classifier: Topic :: Software Development :: Libraries :: Python Modules
Classifier: Topic :: Text Processing :: Filters
Classifier: Typing :: Typed
Requires-Python: >=3.8
Requires-Dist: surt
Provides-Extra: dev
Requires-Dist: pre-commit>=3.0.0; extra == 'dev'
Requires-Dist: pytest-cov>=4.0.0; extra == 'dev'
Requires-Dist: pytest>=7.0.0; extra == 'dev'
Requires-Dist: ruff>=0.1.0; extra == 'dev'
Requires-Dist: twine>=4.0.0; extra == 'dev'
